selenium_uniq_driver/__init__.py
selenium_uniq_driver/data.py
selenium_uniq_driver/params.py
selenium_uniq_driver/randomizer.py
selenium_uniq_driver/stealth.py
selenium_uniq_driver/uniq_driver.py
selenium_uniq_driver/js/for_audio.js
selenium_uniq_driver/js/for_canvas.js
selenium_uniq_driver/js/for_webgl.js
tests/__init__.py
tests/helper.py
tests/test_audio_fingerprint.py
tests/test_canvas_fingerprint.py
tests/test_resolution.py
tests/test_timezone.py
tests/test_user_agent.py
tests/test_webgl_renderer.py
selenium_uniq_driver-1.0.5.dist-info/LICENSE
selenium_uniq_driver-1.0.5.dist-info/METADATA
selenium_uniq_driver-1.0.5.dist-info/WHEEL
selenium_uniq_driver-1.0.5.dist-info/top_level.txt
selenium_uniq_driver-1.0.5.dist-info/RECORD
