Metadata-Version: 2.2
Name: selenium-uniq-driver
Version: 1.0.5
Summary: Create uniq selenium webdriver.
Home-page: https://github.com/AlexanderTsk/selenium-uniq-driver
Author: AlexanderTsk
Author-email: alex13jixy@gmail.com
Classifier: Programming Language :: Python :: 3
Classifier: License :: OSI Approved :: MIT License
Classifier: Operating System :: OS Independent
Requires-Python: >=3.6
License-File: LICENSE
Requires-Dist: blinker==1.4
Requires-Dist: selenium-stealth
Requires-Dist: selenium-wire
Requires-Dist: random-user-agent
Requires-Dist: setuptools
Requires-Dist: pytest
Dynamic: author
Dynamic: author-email
Dynamic: classifier
Dynamic: description
Dynamic: description-content-type
Dynamic: home-page
Dynamic: requires-dist
Dynamic: requires-python
Dynamic: summary
